{
  "project_info": {
    "project_number": "689805027351",
    "project_id": "current-diary-55090",
    "storage_bucket": "current-diary-55090.firebasestorage.app"
  },
  "client": [
    {
      "client_info": {
        "mobilesdk_app_id": "1:689805027351:android:dd0575b4da0ebfe8105452",
        "android_client_info": {
          "package_name": "com.currentDiaryIosApp.app"
        }
      },
      "oauth_client": [],
      "api_key": [
        {
          "current_key": "AIzaSyBSasxjlHTI5Xd7BDH3gfgpZQwkh8Cg6J4"
        }
      ],
      "services": {
        "appinvite_service": {
          "other_platform_oauth_client": []
        }
      }
    }
  ],
  "configuration_version": "1"
}